{"id": "1057802916238471199", "type": 0, "content": "ill make a gc for now", "channel_id": "1057802346488410205", "author": {"id": "927065997536534530", "username": "quacky?", "avatar": "47abdfa1af88e850b88c67428b969f4f", "avatar_decoration": null, "discriminator": "2079", "public_flags": 0}, "attachments": [], "embeds": [], "mentions": [], "mention_roles": [], "pinned": false, "mention_everyone": false, "tts": false, "timestamp": "2022-12-28T23:31:08.259000+00:00", "edited_timestamp": null, "flags": 0, "components": []}
{"id": "1057802512167608481", "type": 0, "content": "Me waiting", "channel_id": "1057802346488410205", "author": {"id": "1011194873346527243", "username": "\u203d\ud835\udd75\ud835\udd8e\ud835\udd86\ud835\udd93-\u30ea\u30e9 \u203d", "avatar": "4b08e8e2d69b46b51482a19fbd989571", "avatar_decoration": null, "discriminator": "3484", "public_flags": 0}, "attachments": [], "embeds": [], "mentions": [], "mention_roles": [], "pinned": false, "mention_everyone": false, "tts": false, "timestamp": "2022-12-28T23:29:31.921000+00:00", "edited_timestamp": null, "flags": 0, "components": []}
{"id": "1057802472434974720", "type": 0, "content": "if u donbt mind u gotta wait for my friend", "channel_id": "1057802346488410205", "author": {"id": "927065997536534530", "username": "quacky?", "avatar": "47abdfa1af88e850b88c67428b969f4f", "avatar_decoration": null, "discriminator": "2079", "public_flags": 0}, "attachments": [], "embeds": [], "mentions": [], "mention_roles": [], "pinned": false, "mention_everyone": false, "tts": false, "timestamp": "2022-12-28T23:29:22.448000+00:00", "edited_timestamp": null, "flags": 0, "components": []}
{"id": "1057802400297123910", "type": 0, "content": "yo", "channel_id": "1057802346488410205", "author": {"id": "927065997536534530", "username": "quacky?", "avatar": "47abdfa1af88e850b88c67428b969f4f", "avatar_decoration": null, "discriminator": "2079", "public_flags": 0}, "attachments": [], "embeds": [], "mentions": [], "mention_roles": [], "pinned": false, "mention_everyone": false, "tts": false, "timestamp": "2022-12-28T23:29:05.249000+00:00", "edited_timestamp": null, "flags": 0, "components": []}
{"id": "1057802388876038204", "type": 0, "content": "Ey", "channel_id": "1057802346488410205", "author": {"id": "1011194873346527243", "username": "\u203d\ud835\udd75\ud835\udd8e\ud835\udd86\ud835\udd93-\u30ea\u30e9 \u203d", "avatar": "4b08e8e2d69b46b51482a19fbd989571", "avatar_decoration": null, "discriminator": "3484", "public_flags": 0}, "attachments": [], "embeds": [], "mentions": [], "mention_roles": [], "pinned": false, "mention_everyone": false, "tts": false, "timestamp": "2022-12-28T23:29:02.526000+00:00", "edited_timestamp": null, "flags": 0, "components": []}
{"id": "1057802362196078664", "type": 0, "content": "", "channel_id": "1057802346488410205", "author": {"id": "927065997536534530", "username": "quacky?", "avatar": "47abdfa1af88e850b88c67428b969f4f", "avatar_decoration": null, "discriminator": "2079", "public_flags": 0}, "attachments": [], "embeds": [], "mentions": [], "mention_roles": [], "pinned": false, "mention_everyone": false, "tts": false, "timestamp": "2022-12-28T23:28:56.165000+00:00", "edited_timestamp": null, "flags": 0, "components": [], "sticker_items": [{"id": "749054660769218631", "format_type": 3, "name": "Wave"}]}
{"id": "1057802916238471199", "type": 0, "content": "ill make a gc for now", "channel_id": "1057802346488410205", "author": {"id": "927065997536534530", "username": "quacky?", "avatar": "47abdfa1af88e850b88c67428b969f4f", "avatar_decoration": null, "discriminator": "2079", "public_flags": 0}, "attachments": [], "embeds": [], "mentions": [], "mention_roles": [], "pinned": false, "mention_everyone": false, "tts": false, "timestamp": "2022-12-28T23:31:08.259000+00:00", "edited_timestamp": null, "flags": 0, "components": []}
{"id": "1057802512167608481", "type": 0, "content": "Me waiting", "channel_id": "1057802346488410205", "author": {"id": "1011194873346527243", "username": "\u203d\ud835\udd75\ud835\udd8e\ud835\udd86\ud835\udd93-\u30ea\u30e9 \u203d", "avatar": "4b08e8e2d69b46b51482a19fbd989571", "avatar_decoration": null, "discriminator": "3484", "public_flags": 0}, "attachments": [], "embeds": [], "mentions": [], "mention_roles": [], "pinned": false, "mention_everyone": false, "tts": false, "timestamp": "2022-12-28T23:29:31.921000+00:00", "edited_timestamp": null, "flags": 0, "components": []}
{"id": "1057802472434974720", "type": 0, "content": "if u donbt mind u gotta wait for my friend", "channel_id": "1057802346488410205", "author": {"id": "927065997536534530", "username": "quacky?", "avatar": "47abdfa1af88e850b88c67428b969f4f", "avatar_decoration": null, "discriminator": "2079", "public_flags": 0}, "attachments": [], "embeds": [], "mentions": [], "mention_roles": [], "pinned": false, "mention_everyone": false, "tts": false, "timestamp": "2022-12-28T23:29:22.448000+00:00", "edited_timestamp": null, "flags": 0, "components": []}
{"id": "1057802400297123910", "type": 0, "content": "yo", "channel_id": "1057802346488410205", "author": {"id": "927065997536534530", "username": "quacky?", "avatar": "47abdfa1af88e850b88c67428b969f4f", "avatar_decoration": null, "discriminator": "2079", "public_flags": 0}, "attachments": [], "embeds": [], "mentions": [], "mention_roles": [], "pinned": false, "mention_everyone": false, "tts": false, "timestamp": "2022-12-28T23:29:05.249000+00:00", "edited_timestamp": null, "flags": 0, "components": []}
{"id": "1057802388876038204", "type": 0, "content": "Ey", "channel_id": "1057802346488410205", "author": {"id": "1011194873346527243", "username": "\u203d\ud835\udd75\ud835\udd8e\ud835\udd86\ud835\udd93-\u30ea\u30e9 \u203d", "avatar": "4b08e8e2d69b46b51482a19fbd989571", "avatar_decoration": null, "discriminator": "3484", "public_flags": 0}, "attachments": [], "embeds": [], "mentions": [], "mention_roles": [], "pinned": false, "mention_everyone": false, "tts": false, "timestamp": "2022-12-28T23:29:02.526000+00:00", "edited_timestamp": null, "flags": 0, "components": []}
{"id": "1057802362196078664", "type": 0, "content": "", "channel_id": "1057802346488410205", "author": {"id": "927065997536534530", "username": "quacky?", "avatar": "47abdfa1af88e850b88c67428b969f4f", "avatar_decoration": null, "discriminator": "2079", "public_flags": 0}, "attachments": [], "embeds": [], "mentions": [], "mention_roles": [], "pinned": false, "mention_everyone": false, "tts": false, "timestamp": "2022-12-28T23:28:56.165000+00:00", "edited_timestamp": null, "flags": 0, "components": [], "sticker_items": [{"id": "749054660769218631", "format_type": 3, "name": "Wave"}]}
